[
  {
    "name": "Cobalt Scar",
    "level_ranges": [[110, 115]],
    "expansion": "Claws of Veeshan",
    "continent": "Velious",
    "zone_type": "Outdoors",
    "connections": ["Kael Drakkel", "Skyshrine", "The Western Wastes"],
    "image_url": "",
    "map_url": "",
    "rating": 0,
    "hot_zone": false,
    "mission": false
  },
  {
    "name": "The Western Wastes",
    "level_ranges": [[110, 115]],
    "expansion": "Claws of Veeshan",
    "continent": "Velious",
    "zone_type": "Outdoors",
    "connections": [
      "Cobalt Scar",
      "Dragon Necropolis",
      "The Temple of Veeshan"
    ],
    "image_url": "",
    "map_url": "",
    "rating": 0,
    "hot_zone": false,
    "mission": false
  },
  {
    "name": "Dragon Necropolis",
    "level_ranges": [[115, 115]],
    "expansion": "Claws of Veeshan",
    "continent": "Velious",
    "zone_type": "Indoors",
    "connections": ["The Western Wastes"],
    "image_url": "",
    "map_url": "",
    "rating": 0,
    "hot_zone": false,
    "mission": false
  },
  {
    "name": "Skyshrine",
    "level_ranges": [[115, 115]],
    "expansion": "Claws of Veeshan",
    "continent": "Velious",
    "zone_type": "Indoors",
    "connections": ["Cobalt Scar"],
    "image_url": "",
    "map_url": "",
    "rating": 0,
    "hot_zone": false,
    "mission": false
  },
  {
    "name": "The Temple of Veeshan",
    "level_ranges": [[115, 115]],
    "expansion": "Claws of Veeshan",
    "continent": "Velious",
    "zone_type": "Indoors",
    "connections": ["The Western Wastes"],
    "image_url": "",
    "map_url": "",
    "rating": 0,
    "hot_zone": false,
    "mission": false
  },
  {
    "name": "The Sleeper's Tomb",
    "level_ranges": [[115, 115]],
    "expansion": "Claws of Veeshan",
    "continent": "Velious",
    "zone_type": "Indoors",
    "connections": ["The Eastern Wastes"],
    "image_url": "",
    "map_url": "",
    "rating": 0,
    "hot_zone": false,
    "mission": false
  }
]
